kafka_connect/__init__.py
kafka_connect/cli.py
kafka_connect/kafka_connect.py
kafka_connect_py-1.0.0.dist-info/METADATA
kafka_connect_py-1.0.0.dist-info/WHEEL
kafka_connect_py-1.0.0.dist-info/entry_points.txt
kafka_connect_py-1.0.0.dist-info/licenses/LICENSE
kafka_connect_py-1.0.0.dist-info/RECORD
