Metadata-Version: 2.4
Name: kafka-connect-py
Version: 1.0.0
Summary: A client for the Confluent Platform Kafka Connect REST API.
License: MIT
License-File: LICENSE
Author: Aidan Melen
Author-email: aidan-melen@protonmail.com
Requires-Python: >=3.8,<4.0
Classifier: License :: OSI Approved :: MIT License
Classifier: Programming Language :: Python :: 3
Classifier: Programming Language :: Python :: 3.8
Classifier: Programming Language :: Python :: 3.9
Classifier: Programming Language :: Python :: 3.10
Classifier: Programming Language :: Python :: 3.11
Classifier: Programming Language :: Python :: 3.12
Classifier: Programming Language :: Python :: 3.13
Classifier: Programming Language :: Python :: 3.14
Requires-Dist: click (>=8.1.3,<9.0.0)
Requires-Dist: requests (>=2.25,<3.0)
Project-URL: Homepage, https://github.com/aidanmelen/kafka-connect-py
Project-URL: Repository, https://github.com/aidanmelen/kafka-connect-py
